CHANGELOG.md
LICENSE
MANIFEST.in
README.md
setup.py
docs/Accessing.md
docs/Administration.md
docs/Index.md
docs/Ingesting.md
docs/Overview.md
docs/Searching.md
docs/Staging.md
hera_librarian/__init__.py
hera_librarian/store.py
hera_librarian/utils.py
hera_librarian.egg-info/PKG-INFO
hera_librarian.egg-info/SOURCES.txt
hera_librarian.egg-info/dependency_links.txt
hera_librarian.egg-info/requires.txt
hera_librarian.egg-info/top_level.txt
scripts/add_librarian_file_event.py
scripts/add_obs_librarian.py
scripts/launch_librarian_copy.py
scripts/librarian_assign_sessions.py
scripts/librarian_delete_files.py
scripts/librarian_initiate_offload.py
scripts/librarian_locate_file.py
scripts/librarian_offload_helper.py
scripts/librarian_set_file_deletion_policy.py
scripts/librarian_stage_files.py
scripts/librarian_stream_file_or_directory.sh
scripts/upload_to_librarian.py
server/README.md
server/alembic.ini
server/plotly_librarian_upload_speed.py
server/plotly_librarian_upload_speed.sh
server/runserver.py
server/server-config.sample.json
server/alembic/backport_instances.sql
server/alembic/env.py
server/alembic/script.py.mako
server/alembic/versions/0e0e6d02a01a_add_index_on_fileevent_name.py
server/alembic/versions/464899566429_make_file_obsids_optional.py
server/alembic/versions/71df5b41ae41_initial_schema.py
server/alembic/versions/b02eb31402b1_add_index_on_fileinstance_name.py
server/alembic/versions/bc996bc8dc1c_add_fileinstance_deletion_policy.py
server/hera_librarian/__init__.py
server/hera_librarian/store.py
server/hera_librarian/utils.py
server/librarian_server/__init__.py
server/librarian_server/bgtasks.py
server/librarian_server/dbutil.py
server/librarian_server/file.py
server/librarian_server/mc_integration.py
server/librarian_server/misc.py
server/librarian_server/observation.py
server/librarian_server/search.py
server/librarian_server/store.py
server/librarian_server/webutil.py
server/librarian_server/templates/file-individual.html
server/librarian_server/templates/layout.html
server/librarian_server/templates/login.html
server/librarian_server/templates/macros.html
server/librarian_server/templates/main-page.html
