Metadata-Version: 1.1
Name: hera-librarian
Version: 0.1.6
Summary: A client for the HERA Librarian data management system
Home-page: https://github.com/HERA-Team/librarian/
Author: HERA Team
Author-email: hera@lists.berkeley.edu
License: BSD
Platform: UNKNOWN
Classifier: Development Status :: 5 - Production/Stable
Classifier: Intended Audience :: Science/Research
Classifier: License :: OSI Approved :: BSD License
Classifier: Topic :: Scientific/Engineering :: Astronomy
